rackfan/__init__.py
rackfan/grid.py
rackfan/rackfan.py
rackfan-0.3.2.dist-info/METADATA
rackfan-0.3.2.dist-info/WHEEL
rackfan-0.3.2.dist-info/entry_points.txt
rackfan-0.3.2.dist-info/top_level.txt
rackfan-0.3.2.dist-info/RECORD
